[
  {
    "id": "1772486042088",
    "discordTag": "vercix__",
    "status": "Odrzucone",
    "date": "2.03.2026",
    "age": "16",
    "exp": "test",
    "terms": "test",
    "charName": "test",
    "charAge": "16",
    "charStory": "test",
    "charGoals": "test",
    "charFlaws": "test"
  },
  {
    "id": "1772489538176",
    "discordId": "1221061191506329795",
    "discordTag": "vercix__",
    "status": "Zaakceptowane",
    "date": "2.03.2026",
    "timestamp": 1772489538189,
    "age": "16",
    "exp": "test",
    "terms": "test",
    "charName": "test",
    "charAge": "15",
    "charStory": "test",
    "charGoals": "test",
    "charFlaws": "test"
  },
  {
    "id": "1772577876384",
    "discordId": "1478522119988969524",
    "discordTag": "adamozio.zapas",
    "status": "Odrzucone",
    "date": "3/3/2026",
    "timestamp": 1772577951044,
    "age": "16",
    "exp": "test",
    "terms": "test",
    "charName": "test",
    "charAge": "16",
    "charStory": "test",
    "charGoals": "test",
    "charFlaws": "test"
  },
  {
    "id": "1772608298542",
    "discordId": "1478522119988969524",
    "discordTag": "adamozio.zapas",
    "status": "Zaakceptowane",
    "date": "3/4/2026",
    "timestamp": 1772608298560,
    "age": "16",
    "exp": "test",
    "terms": "test",
    "charName": "test",
    "charAge": "16",
    "charStory": "test",
    "charGoals": "test",
    "charFlaws": "test"
  }
]